README.md
setup.py
lbrlabs_ovh/__init__.py
lbrlabs_ovh/_inputs.py
lbrlabs_ovh/_utilities.py
lbrlabs_ovh/cloud_project.py
lbrlabs_ovh/cloud_project_container_registry.py
lbrlabs_ovh/cloud_project_container_registry_user.py
lbrlabs_ovh/cloud_project_database.py
lbrlabs_ovh/cloud_project_database_ip_restriction.py
lbrlabs_ovh/cloud_project_database_postgres_sql_user.py
lbrlabs_ovh/cloud_project_database_user.py
lbrlabs_ovh/cloud_project_failover_ip_attach.py
lbrlabs_ovh/cloud_project_kube.py
lbrlabs_ovh/cloud_project_kube_ip_restrictions.py
lbrlabs_ovh/cloud_project_kube_node_pool.py
lbrlabs_ovh/cloud_project_kube_oidc.py
lbrlabs_ovh/cloud_project_network_private.py
lbrlabs_ovh/cloud_project_network_private_subnet.py
lbrlabs_ovh/cloud_project_user.py
lbrlabs_ovh/dbaas_logs_input.py
lbrlabs_ovh/dbaas_logs_output_graylog_stream.py
lbrlabs_ovh/dedicated_ceph_acl.py
lbrlabs_ovh/dedicated_server_reboot_task.py
lbrlabs_ovh/dedicated_server_update.py
lbrlabs_ovh/dedicated_service_install_task.py
lbrlabs_ovh/domain_zone.py
lbrlabs_ovh/domain_zone_record.py
lbrlabs_ovh/domain_zone_redirection.py
lbrlabs_ovh/get_cloud_project_capabilities_container_filter.py
lbrlabs_ovh/get_cloud_project_capabilities_container_registry.py
lbrlabs_ovh/get_cloud_project_container_registries.py
lbrlabs_ovh/get_cloud_project_container_registry.py
lbrlabs_ovh/get_cloud_project_container_registry_users.py
lbrlabs_ovh/get_cloud_project_database.py
lbrlabs_ovh/get_cloud_project_database_ip_restrictions.py
lbrlabs_ovh/get_cloud_project_database_postgres_sql_user.py
lbrlabs_ovh/get_cloud_project_database_user.py
lbrlabs_ovh/get_cloud_project_database_users.py
lbrlabs_ovh/get_cloud_project_databases.py
lbrlabs_ovh/get_cloud_project_failover_ip_attach.py
lbrlabs_ovh/get_cloud_project_kube.py
lbrlabs_ovh/get_cloud_project_kube_ip_node_pool.py
lbrlabs_ovh/get_cloud_project_kube_ip_restrictions.py
lbrlabs_ovh/get_cloud_project_region.py
lbrlabs_ovh/get_cloud_project_regions.py
lbrlabs_pulumi_ovh.egg-info/PKG-INFO
lbrlabs_pulumi_ovh.egg-info/SOURCES.txt
lbrlabs_pulumi_ovh.egg-info/dependency_links.txt
lbrlabs_pulumi_ovh.egg-info/not-zip-safe
lbrlabs_pulumi_ovh.egg-info/requires.txt
lbrlabs_pulumi_ovh.egg-info/top_level.txt
